publishcanary/__init__.py
publishcanary/cli.py
publishcanary/publishcanary.py
cansync-0.0.1.dist-info/METADATA
cansync-0.0.1.dist-info/WHEEL
cansync-0.0.1.dist-info/entry_points.txt
cansync-0.0.1.dist-info/top_level.txt
cansync-0.0.1.dist-info/RECORD
